Workbook

Sheet Dashboard
B2: Areomoon 財富自由追蹤儀表板
B3: 2026-2036 | 風險容忍度：低 | 目標：10 年內達成家庭財務獨立
B5: 關鍵指標（來自 Monthly Tracker 最新月份）
B6: 淨資產 (Net Worth) | E6: =INDEX('Monthly Tracker'!P:P,MATCH(MAX('Monthly Tracker'!A:A),'Monthly Tracker'!A:A,0)) -> 0
B7: 投資組合總值 | E7: =INDEX('Monthly Tracker'!N:N,MATCH(MAX('Monthly Tracker'!A:A),'Monthly Tracker'!A:A,0)) -> 0
B8: 流動現金 | E8: =INDEX('Monthly Tracker'!M:M,MATCH(MAX('Monthly Tracker'!A:A),'Monthly Tracker'!A:A,0)) -> 0
B9: 本月總收入 | E9: =INDEX('Monthly Tracker'!H:H,MATCH(MAX('Monthly Tracker'!A:A),'Monthly Tracker'!A:A,0)) -> 0
B10: 本月儲蓄率 | E10: =IFERROR(INDEX('Monthly Tracker'!L:L,MATCH(MAX('Monthly Tracker'!A:A),'Monthly Tracker'!A:A,0)),0) -> 0
B11: 距離 5 年目標 | E11: =IFERROR(1 - INDEX('Monthly Tracker'!P:P,MATCH(MAX('Monthly Tracker'!A:A),'Monthly Tracker'!A:A,0))/Assumptions!B16,1) -> 1
B13: 家庭 Milestone 倒數
B14: Milestone | C14: 目標日期 | D14: 距離今天 | E14: 預算 (SGD) | F14: 目前儲蓄 | G14: 完成度
B15: 結婚 | C15: =Milestones!B3 -> 46752 | D15: =Milestones!D3 -> 630 | E15: =Milestones!E3 -> 80000 | F15: =Milestones!F3 -> 0 | G15: =IFERROR(F15/E15,0) -> 0
B16: 購屋頭期款 | C16: =Milestones!B4 -> 47299 | D16: =Milestones!D4 -> 1177 | E16: =Milestones!E4 -> 400000 | F16: =Milestones!F4 -> 0 | G16: =IFERROR(F16/E16,0) -> 0
B17: 第一胎 | C17: =Milestones!B5 -> 47664 | D17: =Milestones!D5 -> 1542 | E17: =Milestones!E5 -> 30000 | F17: =Milestones!F5 -> 0 | G17: =IFERROR(F17/E17,0) -> 0
B18: 緊急備用金 | C18: =Milestones!B6 -> 46387 | D18: =Milestones!D6 -> 265 | E18: =Milestones!E6 -> 100000 | F18: =Milestones!F6 -> 0 | G18: =IFERROR(F18/E18,0) -> 0
B21: 下個月行動清單
B22: 1. 更新 Monthly Tracker — 填入本月收入、支出、投資餘額
B23: 2. 檢查緊急備用金是否達到 12 個月開銷門檻
B24: 3. Review 四軌進度表，標註本月關鍵事件
B25: 4. 投資組合 rebalance（若偏離目標配置 > 5%）
B26: 5. LinkedIn 發 1-2 篇技術文章（軌道 2 品牌）
B27: 6. 與伴侶每月財務 check-in

Sheet Monthly Tracker
A1: 月度財務追蹤表
A2: 每月填寫藍色欄位，其他欄位自動計算。A 欄為月份（輸入每月 1 日）
A3: 月份 | B3: 主業薪資 (SGD) | C3: 獎金 (SGD) | D3: 諮詢收入 | E3: 產品收入 | F3: 投資股息 | G3: 其他收入 | H3: 總收入 | I3: 固定支出 | J3: 變動支出 | K3: 總支出 | L3: 儲蓄率 | M3: 流動現金 | N3: 投資組合 | O3: 其他資產 | P3: 淨資產
A4: 46113 | B4: 0 | C4: 0 | D4: 0 | E4: 0 | F4: 0 | G4: 0 | H4: =SUM(B4:G4) -> 0 | I4: 0 | J4: 0 | K4: =I4+J4 -> 0 | L4: =IFERROR((H4-K4)/H4,0) -> 0 | M4: 0 | N4: 0 | O4: 0 | P4: =M4+N4+O4 -> 0
A5: 46143 | B5: 0 | C5: 0 | D5: 0 | E5: 0 | F5: 0 | G5: 0 | H5: =SUM(B5:G5) -> 0 | I5: 0 | J5: 0 | K5: =I5+J5 -> 0 | L5: =IFERROR((H5-K5)/H5,0) -> 0 | M5: 0 | N5: 0 | O5: 0 | P5: =M5+N5+O5 -> 0
A6: 46174 | B6: 0 | C6: 0 | D6: 0 | E6: 0 | F6: 0 | G6: 0 | H6: =SUM(B6:G6) -> 0 | I6: 0 | J6: 0 | K6: =I6+J6 -> 0 | L6: =IFERROR((H6-K6)/H6,0) -> 0 | M6: 0 | N6: 0 | O6: 0 | P6: =M6+N6+O6 -> 0
A7: 46204 | B7: 0 | C7: 0 | D7: 0 | E7: 0 | F7: 0 | G7: 0 | H7: =SUM(B7:G7) -> 0 | I7: 0 | J7: 0 | K7: =I7+J7 -> 0 | L7: =IFERROR((H7-K7)/H7,0) -> 0 | M7: 0 | N7: 0 | O7: 0 | P7: =M7+N7+O7 -> 0
A8: 46235 | B8: 0 | C8: 0 | D8: 0 | E8: 0 | F8: 0 | G8: 0 | H8: =SUM(B8:G8) -> 0 | I8: 0 | J8: 0 | K8: =I8+J8 -> 0 | L8: =IFERROR((H8-K8)/H8,0) -> 0 | M8: 0 | N8: 0 | O8: 0 | P8: =M8+N8+O8 -> 0
A9: 46266 | B9: 0 | C9: 0 | D9: 0 | E9: 0 | F9: 0 | G9: 0 | H9: =SUM(B9:G9) -> 0 | I9: 0 | J9: 0 | K9: =I9+J9 -> 0 | L9: =IFERROR((H9-K9)/H9,0) -> 0 | M9: 0 | N9: 0 | O9: 0 | P9: =M9+N9+O9 -> 0
A10: 46296 | B10: 0 | C10: 0 | D10: 0 | E10: 0 | F10: 0 | G10: 0 | H10: =SUM(B10:G10) -> 0 | I10: 0 | J10: 0 | K10: =I10+J10 -> 0 | L10: =IFERROR((H10-K10)/H10,0) -> 0 | M10: 0 | N10: 0 | O10: 0 | P10: =M10+N10+O10 -> 0
A11: 46327 | B11: 0 | C11: 0 | D11: 0 | E11: 0 | F11: 0 | G11: 0 | H11: =SUM(B11:G11) -> 0 | I11: 0 | J11: 0 | K11: =I11+J11 -> 0 | L11: =IFERROR((H11-K11)/H11,0) -> 0 | M11: 0 | N11: 0 | O11: 0 | P11: =M11+N11+O11 -> 0
A12: 46357 | B12: 0 | C12: 0 | D12: 0 | E12: 0 | F12: 0 | G12: 0 | H12: =SUM(B12:G12) -> 0 | I12: 0 | J12: 0 | K12: =I12+J12 -> 0 | L12: =IFERROR((H12-K12)/H12,0) -> 0 | M12: 0 | N12: 0 | O12: 0 | P12: =M12+N12+O12 -> 0
A13: 46388 | B13: 0 | C13: 0 | D13: 0 | E13: 0 | F13: 0 | G13: 0 | H13: =SUM(B13:G13) -> 0 | I13: 0 | J13: 0 | K13: =I13+J13 -> 0 | L13: =IFERROR((H13-K13)/H13,0) -> 0 | M13: 0 | N13: 0 | O13: 0 | P13: =M13+N13+O13 -> 0
A14: 46419 | B14: 0 | C14: 0 | D14: 0 | E14: 0 | F14: 0 | G14: 0 | H14: =SUM(B14:G14) -> 0 | I14: 0 | J14: 0 | K14: =I14+J14 -> 0 | L14: =IFERROR((H14-K14)/H14,0) -> 0 | M14: 0 | N14: 0 | O14: 0 | P14: =M14+N14+O14 -> 0
A15: 46447 | B15: 0 | C15: 0 | D15: 0 | E15: 0 | F15: 0 | G15: 0 | H15: =SUM(B15:G15) -> 0 | I15: 0 | J15: 0 | K15: =I15+J15 -> 0 | L15: =IFERROR((H15-K15)/H15,0) -> 0 | M15: 0 | N15: 0 | O15: 0 | P15: =M15+N15+O15 -> 0
... A27: 46813 | B27: 0 | C27: 0 | D27: 0 | E27: 0 | F27: 0 | G27: 0 | H27: =SUM(B27:G27) -> 0 | I27: 0 | J27: 0 | K27: =I27+J27 -> 0 | L27: =IFERROR((H27-K27)/H27,0) -> 0 | M27: 0 | N27: 0 | O27: 0 | P27: =M27+N27+O27 -> 0
A30: 色彩說明：
A31: 藍色 = 手動輸入
A32: 黑色 = 自動計算
A33: 綠色 = 跨工作表連結

Sheet Investment Portfolio
A1: 投資組合配置與追蹤
A2: 追蹤各資產類別的配置是否符合目標。偏離超過 5% 時建議 rebalance。
A4: 資產類別 | B4: 目標配置 | C4: 當前市值 (SGD) | D4: 實際配置 | E4: 偏差 | F4: 狀態
A5: 全球股票 Index (VWRA) | B5: 0.6 | C5: 0 | D5: =IFERROR(C5/$C$10,0) -> 0 | E5: =D5-B5 -> -0.6 | F5: =IF(ABS(E5)>0.05,"⚠ Rebalance","✓ OK") -> ⚠ Rebalance
A6: 美國股票 Index (VOO/VTI) | B6: 0.15 | C6: 0 | D6: =IFERROR(C6/$C$10,0) -> 0 | E6: =D6-B6 -> -0.15 | F6: =IF(ABS(E6)>0.05,"⚠ Rebalance","✓ OK") -> ⚠ Rebalance
A7: 債券 (SSB, AGG) | B7: 0.1 | C7: 0 | D7: =IFERROR(C7/$C$10,0) -> 0 | E7: =D7-B7 -> -0.1 | F7: =IF(ABS(E7)>0.05,"⚠ Rebalance","✓ OK") -> ⚠ Rebalance
A8: REITs (CLR, Lion-Phillip) | B8: 0.1 | C8: 0 | D8: =IFERROR(C8/$C$10,0) -> 0 | E8: =D8-B8 -> -0.1 | F8: =IF(ABS(E8)>0.05,"⚠ Rebalance","✓ OK") -> ⚠ Rebalance
A9: 衛星配置 (個別股/BTC) | B9: 0.05 | C9: 0 | D9: =IFERROR(C9/$C$10,0) -> 0 | E9: =D9-B9 -> -0.05 | F9: =IF(ABS(E9)>0.05,"⚠ Rebalance","✓ OK") -> ✓ OK
A10: 總計 | B10: =SUM(B5:B9) -> 1 | C10: =SUM(C5:C9) -> 0 | D10: =SUM(D5:D9) -> 0
A13: Rebalance 規則
A14: 1. 每季檢查一次配置
A15: 2. 偏差超過 5% 時 rebalance
A16: 3. Rebalance 方法：新資金優先買入 underweight 類別（避免賣出的稅務成本）
A17: 4. 避免頻繁 rebalance（每年最多 2-3 次）
A18: 5. 大跌時（-15% 以上）加碼股票類，不要恐慌出場

Sheet Four Tracks Progress
A1: 四軌策略進度追蹤
A2: 每季更新一次，追蹤各軌道的關鍵指標進度
A4: 軌道 | B4: 指標 | C4: 當前值 | D4: 年底目標 | E4: 3 年目標 | F4: 進度
A5: 軌道 1: W2 職涯 | B5: 年薪 (SGD total comp) | C5: 150000 | D5: 180000 | E5: 300000 | F5: =IFERROR(C5/D5,0) -> 0.83333333
B6: 職級 (0=入職, 1=Senior, 2=Staff) | C6: 0 | D6: 0 | E6: 1 | F6: =IFERROR(C6/D6,0) -> 0
B7: Performance Rating | C7: 0 | D7: 4 | E7: 5 | F7: =IFERROR(C7/D7,0) -> 0
B8: Technical Talks (每季) | C8: 0 | D8: 1 | E8: 4 | F8: =IFERROR(C8/D8,0) -> 0
B9: Network contacts (累積) | C9: 0 | D9: 30 | E9: 150 | F9: =IFERROR(C9/D9,0) -> 0
A10: 軌道 2: Side Project | B10: ai_daily_digest MRR (USD) | C10: 0 | D10: 500 | E10: 3000 | F10: =IFERROR(C10/D10,0) -> 0
B11: 付費用戶數 | C11: 0 | D11: 50 | E11: 300 | F11: =IFERROR(C11/D11,0) -> 0
B12: LinkedIn 追蹤者 | C12: 0 | D12: 1000 | E12: 5000 | F12: =IFERROR(C12/D12,0) -> 0
B13: Technical Articles 發表數 | C13: 0 | D13: 24 | E13: 100 | F13: =IFERROR(C13/D13,0) -> 0
B14: GitHub Stars 累積 | C14: 0 | D14: 200 | E14: 1500 | F14: =IFERROR(C14/D14,0) -> 0
A15: 軌道 3: 諮詢/教學 | B15: 累積諮詢收入 (USD) | C15: 0 | D15: 5000 | E15: 50000 | F15: =IFERROR(C15/D15,0) -> 0
B16: Course 學員數 | C16: 0 | D16: 0 | E16: 500 | F16: =IFERROR(C16/D16,0) -> 0
B17: 企業內訓場次 | C17: 0 | D17: 0 | E17: 6 | F17: =IFERROR(C17/D17,0) -> 0
B18: Advisor 職位數 | C18: 0 | D18: 0 | E18: 2 | F18: =IFERROR(C18/D18,0) -> 0
A19: 軌道 4: 投資 | B19: 月定額 (SGD) | C19: 3000 | D19: 5000 | E19: 15000 | F19: =IFERROR(C19/D19,0) -> 0.6
B20: 投資組合總值 (SGD) | C20: 0 | D20: 50000 | E20: 350000 | F20: =IFERROR(C20/D20,0) -> 0
B21: 年化報酬率 | C21: 0 | D21: 0.07 | E21: 0.08 | F21: =IFERROR(C21/D21,0) -> 0
B22: 股息被動收入 (年 SGD) | C22: 0 | D22: 1500 | E22: 15000 | F22: =IFERROR(C22/D22,0) -> 0

Sheet Milestones
A1: 家庭 Milestone 與倒數計時
A2: Milestone | B2: 目標日期 | C2: 備註 | D2: 距離今天（天） | E2: 預算 (SGD) | F2: 目前儲蓄 (SGD)
A3: 結婚 | B3: 46752 | C3: 預算含婚禮 + 蜜月 | D3: =B3-TODAY() -> 630 | E3: 80000 | F3: 0
A4: 購屋頭期款 | B4: 47299 | C4: HDB Resale 或 Condo 頭期 25-30% | D4: =B4-TODAY() -> 1177 | E4: 400000 | F4: 0
A5: 第一胎 | B5: 47664 | C5: 出生費用 + 第一年育兒用品 | D5: =B5-TODAY() -> 1542 | E5: 30000 | F5: 0
A6: 緊急備用金完成 | B6: 46387 | C6: 12 個月家庭開銷 | D6: =B6-TODAY() -> 265 | E6: 100000 | F6: 0
A7: 孩子教育金啟動 | B7: 47848 | C7: 每月定額 S$800 投入 | D7: =B7-TODAY() -> 1726 | E7: 10000 | F7: 0
A10: 提示：當「距離今天」小於 180 天時要加緊儲蓄

Sheet Insurance Checklist
A1: 保險覆蓋檢查清單
A2: 原則：買保障不買儲蓄險；總保費控制在家庭收入 8-12%
A4: 保險類型 | B4: 建議保額 | C4: 年保費 (SGD) | D4: 供應商 | E4: 已投保 | F4: 到期日
A5: 定期壽險 (Term Life) | B5: 年收入 10-15 倍 | C5: 待報價 | D5: AIA/NTUC/Great Eastern | E5: 否
A6: 重大疾病險 | B6: S$300-500k | C6: 待報價 | D6: AIA/Prudential | E6: 否
A7: 收入保障險 | B7: 月收入 60-70% | C7: 待報價 | D7: Manulife/AIA | E7: 否
A8: Integrated Shield Plan | B8: Private 私立醫院 | C8: 約 S$500-1500 | D8: AIA/NTUC/Great Eastern | E8: 否
A9: 旅遊險 (年約) | B9: 含醫療 S$200k+ | C9: 約 S$300-500 | D9: NTUC/MSIG | E9: 否
A10: CPF MediShield Life | B10: 基本 | C10: CPF 自動扣 | D10: 政府 | E10: 是 | F10: 終生

Sheet 10-Year Projection
A1: 10 年淨值預估 (三情境)
A2: 假設值可在 Assumptions 工作表調整，此工作表自動計算
A4: 年份 | B4: 月定額投入 (SGD) | C4: 保守情境淨值 (7%) | D4: 基準情境淨值 (8%) | E4: 樂觀情境淨值 (9%) | F4: 家庭支出 (估算) | G4: 距離目標
A5: 2026 | B5: =Assumptions!B4 -> 3000 | C5: =Assumptions!B3+B5*12 -> 86000 | D5: =Assumptions!B3+B5*12 -> 86000 | E5: =Assumptions!B3+B5*12 -> 86000 | F5: =Assumptions!B9*12 -> 72000 | G5: =IFERROR(1-D5/Assumptions!B17,1) -> -2149999
A6: 2027 | B6: =B5*(1+Assumptions!B5) -> 3450 | C6: =C5*(1+Assumptions!B6)+B6*12 -> 133420 | D6: =D5*(1+Assumptions!B7)+B6*12 -> 134280 | E6: =E5*(1+Assumptions!B8)+B6*12 -> 135140 | F6: =F5*(1+Assumptions!B10) -> 74520 | G6: =IFERROR(1-D6/Assumptions!B17,1) -> -3356999
A7: 2028 | B7: =B6*(1+Assumptions!B5) -> 3967.5 | C7: =C6*(1+Assumptions!B6)+B7*12 -> 190369.4 | D7: =D6*(1+Assumptions!B7)+B7*12 -> 192632.4 | E7: =E6*(1+Assumptions!B8)+B7*12 -> 194912.6 | F7: =F6*(1+Assumptions!B10) -> 77128.2 | G7: =IFERROR(1-D7/Assumptions!B17,1) -> -4815809
A8: 2029 | B8: =B7*(1+Assumptions!B5) -> 4562.625 | C8: =C7*(1+Assumptions!B6)+B8*12 -> 258446.76 | D8: =D7*(1+Assumptions!B7)+B8*12 -> 262794.49 | E8: =E7*(1+Assumptions!B8)+B8*12 -> 267206.23 | F8: =F7*(1+Assumptions!B10) -> 79827.687 | G8: =IFERROR(1-D8/Assumptions!B17,1) -> -6569861.3
A9: 2030 | B9: =B8*(1+Assumptions!B5) -> 5247.0188 | C9: =C8*(1+Assumptions!B6)+B9*12 -> 339502.26 | D9: =D8*(1+Assumptions!B7)+B9*12 -> 346782.28 | E9: =E8*(1+Assumptions!B8)+B9*12 -> 354219.02 | F9: =F8*(1+Assumptions!B10) -> 82621.656 | G9: =IFERROR(1-D9/Assumptions!B17,1) -> -8669555.9
A10: 2031 | B10: =B9*(1+Assumptions!B5) -> 6034.0716 | C10: =C9*(1+Assumptions!B6)+B10*12 -> 435676.27 | D10: =D9*(1+Assumptions!B7)+B10*12 -> 446933.72 | E10: =E9*(1+Assumptions!B8)+B10*12 -> 458507.59 | F10: =F9*(1+Assumptions!B10) -> 85513.414 | G10: =IFERROR(1-D10/Assumptions!B17,1) -> -11173342
A11: 2032 | B11: =B10*(1+Assumptions!B5) -> 6939.1823 | C11: =C10*(1+Assumptions!B6)+B11*12 -> 549443.8 | D11: =D10*(1+Assumptions!B7)+B11*12 -> 565958.6 | E11: =E10*(1+Assumptions!B8)+B11*12 -> 583043.46 | F11: =F10*(1+Assumptions!B10) -> 88506.383 | G11: =IFERROR(1-D11/Assumptions!B17,1) -> -14148964
A12: 2033 | B12: =B11*(1+Assumptions!B5) -> 7980.0596 | C12: =C11*(1+Assumptions!B6)+B12*12 -> 683665.58 | D12: =D11*(1+Assumptions!B7)+B12*12 -> 706996.01 | E12: =E11*(1+Assumptions!B8)+B12*12 -> 731278.09 | F12: =F11*(1+Assumptions!B10) -> 91604.107 | G12: =IFERROR(1-D12/Assumptions!B17,1) -> -17674899
A13: 2034 | B13: =B12*(1+Assumptions!B5) -> 9177.0686 | C13: =C12*(1+Assumptions!B6)+B13*12 -> 841646.99 | D13: =D12*(1+Assumptions!B7)+B13*12 -> 873680.51 | E13: =E12*(1+Assumptions!B8)+B13*12 -> 907217.94 | F13: =F12*(1+Assumptions!B10) -> 94810.251 | G13: =IFERROR(1-D13/Assumptions!B17,1) -> -21842012
A14: 2035 | B14: =B13*(1+Assumptions!B5) -> 10553.629 | C14: =C13*(1+Assumptions!B6)+B14*12 -> 1027205.8 | D14: =D13*(1+Assumptions!B7)+B14*12 -> 1070218.5 | E14: =E13*(1+Assumptions!B8)+B14*12 -> 1115511.1 | F14: =F13*(1+Assumptions!B10) -> 98128.609 | G14: =IFERROR(1-D14/Assumptions!B17,1) -> -26755461
A15: 2036 | B15: =B14*(1+Assumptions!B5) -> 12136.673 | C15: =C14*(1+Assumptions!B6)+B15*12 -> 1244750.3 | D15: =D14*(1+Assumptions!B7)+B15*12 -> 1301476.1 | E15: =E14*(1+Assumptions!B8)+B15*12 -> 1361547.2 | F15: =F14*(1+Assumptions!B10) -> 101563.11 | G15: =IFERROR(1-D15/Assumptions!B17,1) -> -32536900

Sheet Assumptions
A1: 核心假設 (所有預估基於這些輸入)
A2: 藍色欄位為輸入，調整這裡的值會更新所有工作表的計算
A3: 起始資產 | B3: 50000 | C3: 目前流動資產 + 投資
A4: 首年月定額投入 | B4: 3000 | C4: SGD/月
A5: 月定額年增長率 | B5: 0.15 | C5: 薪水增加後月定額也增加
A6: 保守情境年化報酬 | B6: 0.07 | C6: 債券多、全市場 ETF
A7: 基準情境年化報酬 | B7: 0.08 | C7: 標準 60/40
A8: 樂觀情境年化報酬 | B8: 0.09 | C8: 股票多一點
A9: 首年家庭月開銷 | B9: 6000 | C9: SGD/月
A10: 通膨率 (支出增長) | B10: 0.035 | C10: SG 歷史平均 2-3%，保守用 3.5%
A12: 財務目標
A13: 緊急備用金目標 | B13: 100000 | C13: 12 個月家庭開銷
A14: 第一個里程碑（財務獨立） | B14: 1500000 | C14: 5 年目標
A15: 舒適獨立目標 | B15: 3000000 | C15: 7 年目標
A16: 完全自由目標 | B16: 5000000 | C16: 10 年目標
A17: 安全提領率 (SWR) | B17: 0.04 | C17: 傳統 4% 規則
